MANIFEST.in
README.md
setup.py
beancount_plugins/__init__.py
beancount_plugins.egg-info/PKG-INFO
beancount_plugins.egg-info/SOURCES.txt
beancount_plugins.egg-info/dependency_links.txt
beancount_plugins.egg-info/not-zip-safe
beancount_plugins.egg-info/top_level.txt
beancount_plugins/plugins/__init__.py
beancount_plugins/plugins/automated_depreciation/depreciate.py
beancount_plugins/plugins/flexible_depreciation/__init__.py
beancount_plugins/plugins/flexible_depreciation/depreciate.py
beancount_plugins/plugins/split_transactions/split_transactions.py
beancount_plugins/plugins/zero_sum/__init__.py
beancount_plugins/plugins/zero_sum/zerosum.py