Metadata-Version: 1.1
Name: beancount-plugins
Version: 0.0.4
Summary: Library of user contributed plugins for beancount
Home-page: https://github.com/davidastephens/beancount-plugins
Author: David Stephens
Author-email: dstephens99@gmail.com
License: BSD License
Platform: UNKNOWN
Classifier: Development Status :: 3 - Alpha
Classifier: Environment :: Console
Classifier: Intended Audience :: Financial and Insurance Industry
Classifier: Operating System :: OS Independent
Classifier: Programming Language :: Python
Classifier: Programming Language :: Python :: 3
Classifier: Programming Language :: Python :: 3.2
Classifier: Programming Language :: Python :: 3.3
Classifier: Programming Language :: Python :: 3.4
Classifier: Topic :: Utilities
